minimal_pr_review_agent/__init__.py
minimal_pr_review_agent/pr_components.py
minimal_pr_review_agent/pr_llm_review.py
minimal_pr_review_agent/llm_request/__init__.py
minimal_pr_review_agent/llm_request/request_gemini.py
minimal_pr_review_agent-0.1.1.dist-info/METADATA
minimal_pr_review_agent-0.1.1.dist-info/WHEEL
minimal_pr_review_agent-0.1.1.dist-info/top_level.txt
minimal_pr_review_agent-0.1.1.dist-info/RECORD
