Metadata-Version: 2.4
Name: minimal-pr-review-agent
Version: 0.1.1
Summary: A minimal PR review agent using LLM for automated code review
Author-email: flyxiv <junyeopna4@gmail.com>
Project-URL: Homepage, https://github.com/flyxiv/minimal-pr-agent
Project-URL: Repository, https://github.com/flyxiv/minimal-pr-agent
Project-URL: Issues, https://github.com/flyxiv/minimal-pr-agent/issues
Classifier: Development Status :: 3 - Alpha
Classifier: Intended Audience :: Developers
Classifier: License :: OSI Approved :: MIT License
Classifier: Programming Language :: Python :: 3
Classifier: Programming Language :: Python :: 3.8
Classifier: Programming Language :: Python :: 3.9
Classifier: Programming Language :: Python :: 3.10
Classifier: Programming Language :: Python :: 3.11
Classifier: Programming Language :: Python :: 3.12
Classifier: Programming Language :: Python :: 3.13
Requires-Python: >=3.8
Requires-Dist: PyGithub>=2.0.0
Requires-Dist: pydantic>=2.0.0
Requires-Dist: httpx>=0.24.0
Requires-Dist: google-generativeai>=0.3.0
Requires-Dist: pyyaml
Requires-Dist: requests
Requires-Dist: pydantic>=2.7.1
Requires-Dist: python-dotenv
